LICENCE.txt
MANIFEST.in
README.rst
setup.py
django_xiti.egg-info/PKG-INFO
django_xiti.egg-info/SOURCES.txt
django_xiti.egg-info/dependency_links.txt
django_xiti.egg-info/not-zip-safe
django_xiti.egg-info/top_level.txt
xiti/__init__.py
xiti/models.py
xiti/settings.py
xiti/templates/xiti/include_js.html
xiti/templates/xiti/xiti_code.html
xiti/templatetags/__init__.py
xiti/templatetags/xiti_tags.py