Metadata-Version: 1.1
Name: django-xiti
Version: 0.1.1
Summary: 
